altqq/__init__.py
altqq/structs.py
altqq/translators/__init__.py
altqq/translators/common.py
altqq/translators/mysql.py
altqq/translators/plain_text.py
altqq/translators/psycopg.py
altqq/translators/pyodbc.py
altqq/types.py
altqq-0.0.9.dist-info/METADATA
altqq-0.0.9.dist-info/WHEEL
altqq-0.0.9.dist-info/licenses/LICENSE
altqq-0.0.9.dist-info/RECORD
