Metadata-Version: 2.4
Name: altqq
Version: 0.0.9
Summary: Alternative Queries: Typed and Reusable Handcrafted SQL
License: MIT
License-File: LICENSE
Keywords: database,SQL
Author: baluyotraf
Author-email: baluyotraf@outlook.com
Maintainer: baluyotraf
Maintainer-email: baluyotraf@outlook.com
Requires-Python: >=3.9,<4.0
Classifier: License :: OSI Approved :: MIT License
Classifier: Programming Language :: Python :: 3
Classifier: Programming Language :: Python :: 3.9
Classifier: Programming Language :: Python :: 3.10
Classifier: Programming Language :: Python :: 3.11
Classifier: Programming Language :: Python :: 3.12
Classifier: Programming Language :: Python :: 3.13
Classifier: Programming Language :: Python :: 3.14
Requires-Dist: pydantic (>=2.6.4,<3.0.0)
Requires-Dist: typing-extensions (>=4.15.0,<5.0.0)
Project-URL: Homepage, https://altqq.baluyotraf.com
Project-URL: Repository, https://github.com/baluyotraf/altqq
